calla2a_on_mcp/__init__.py
calla2a_on_mcp/__main__.py
calla2a_on_mcp/hostfault_agent_executor.py
calla2a_on_mcp/run_a2a_server.py
calla2a_on_mcp/run_mcp_server.py
calla2a_on_mcp-0.1.0.dist-info/METADATA
calla2a_on_mcp-0.1.0.dist-info/WHEEL
calla2a_on_mcp-0.1.0.dist-info/entry_points.txt
calla2a_on_mcp-0.1.0.dist-info/RECORD
