Metadata-Version: 2.4
Name: calla2a-on-mcp
Version: 0.1.0
Summary: Add your description here
Requires-Python: >=3.13
Requires-Dist: a2a-sdk>=0.2.9
Requires-Dist: click>=8.0.80
Requires-Dist: mcp>=1.11.0
